{
  "schemaVersion": 1,
  "id": "boringmods",
  "version": "${version}",

  "name": "Boring Mods",
  "description": "Minecraft Mods boring.",
  "authors": [
    "Mack Fire"
  ],
  "contact": {
    "homepage": "https://fabricmc.net/",
    "sources": "https://github.com/MackZxh/BoringMods"
  },
  "license": "Apache-2.0",
  "icon": "assets/boringmods/icon.png",

  "environment": "*",
  "entrypoints": {
    "client": [
      "net.mack.boringmods.init.ClientInitializer"
    ],
    "main": [
      "net.mack.boringmods.init.ModInitializer"
    ]
  },
  "mixins": [
    "boringmods.mixins.json"
  ],

  "requires": {
    "fabricloader": ">=0.4.0",
    "fabric": "*"
  }
}
